MANIFEST.in
README.md
requirements.txt
setup.py
infraless/__init__.py
infraless/bootstrap.py
infraless/cli_router.py
infraless.egg-info/PKG-INFO
infraless.egg-info/SOURCES.txt
infraless.egg-info/dependency_links.txt
infraless.egg-info/entry_points.txt
infraless.egg-info/requires.txt
infraless.egg-info/top_level.txt
infraless/controllers/__init__.py
infraless/controllers/base.py
infraless/controllers/generate.py
infraless/controllers/validators.py
infraless/core/__init__.py
infraless/core/config.py
infraless/core/exc.py
infraless/core/helpers.py
infraless/core/version.py
infraless/ext/__init__.py
infraless/templates/__init__.py