Metadata-Version: 2.1
Name: infraless
Version: 0.0.6a0
Summary: Run your code at scale without worrying about the cloud
Home-page: https://github.com/ispulkit
Author: Pulkit Kumar
Author-email: ispulkitkr@gmail.com
License: unlicensed
Platform: UNKNOWN
